{
{"geometry":"{u'type': u'MultiPolygon',"id": u'coordinates': [[[[986450.4858028748,"type": 203647.59750692078],"properties": [986409.4773426198},
{"geometry":"{u'type': u'Polygon',"id": u'coordinates': [[[991584.9213858142,"type": 215367.7026454836],"properties": [991458.1048487064},
{"geometry":"{u'type': u'Polygon',"id": u'coordinates': [[[996495.7425005415,"type": 226338.30782364155],"properties": [996361.8412743466},
{"geometry":"{u'type': u'Polygon',"id": u'coordinates': [[[1000029.3494502797,"type": 242245.0562882213],"properties": [1000475.609031661},
{"geometry":"{u'type': u'MultiPolygon',"id": u'coordinates': [[[[998501.293113125,"type": 243072.61207780757],"properties": [998389.1722464067},
{"geometry":"{u'type': u'Polygon',"id": u'coordinates': [[[996462.556808496,"type": 233948.5189062576],"properties": [996588.120610217},
{"geometry":"{u'type': u'Polygon',"id": u'coordinates': [[[983251.1616685012,"type": 199277.00750293527],"properties": [983386.4526643038},
{"geometry":"{u'type': u'MultiPolygon',"id": u'coordinates': [[[[991853.118223011,"type": 217950.90497730224],"properties": [991978.8092200847},
{"geometry":"{u'type': u'MultiPolygon',"id": u'coordinates': [[[[999588.4017670443,"type": 231919.4891602897],"properties": [999163.5662625922},
{"geometry":"{u'type': u'Polygon',"id": u'coordinates': [[[987894.358415539,"type": 208704.6901011634],"properties": [988028.1679495912},
{"geometry":"{u'type': u'MultiPolygon',"id": u'coordinates': [[[[938813.4980441337,"type": 155500.9898009273],"properties": [938839.8124418639},
{"geometry":"{u'type': u'MultiPolygon',"id": u'coordinates': [[[[938813.4980441337,"type": 155500.9898009273],"properties": [938594.7255221345},
{"geometry":"{u'type': u'MultiPolygon',"id": u'coordinates': [[[[955888.2233606284,"type": 161648.23041194482],"properties": [955334.5542936631},
{"geometry":"{u'type': u'Polygon',"id": u'coordinates': [[[1015870.3135481084,"type": 259501.77712066498],"properties": [1015837.3449168252},
{"geometry":"{u'type': u'MultiPolygon',"id": u'coordinates': [[[[1028926.1873416408,"type": 265049.75515317736],"properties": [1029213.6053550191},
{"geometry":"{u'type': u'Polygon',"id": u'coordinates': [[[1019235.5830749933,"type": 245262.20695148365],"properties": [1019473.8432448163},
{"geometry":"{u'type': u'Polygon',"id": u'coordinates': [[[1010266.0532038365,"type": 244781.2887672721],"properties": [1010000.7346027227},
{"geometry":"{u'type': u'Polygon',"id": u'coordinates': [[[1025507.0689222594,"type": 246350.14673249362],"properties": [1025418.8293844921},
{"geometry":"{u'type': u'MultiPolygon',"id": u'coordinates': [[[[1004093.9238602464,"type": 232209.48919482657],"properties": [1003663.1658093366},
{"geometry":"{u'type': u'MultiPolygon',"id": u'coordinates': [[[[1020315.4613827787,"type": 245130.44210369],"properties": [1020401.7273076893},
{"geometry":"{u'type': u'Polygon',"id": u'coordinates': [[[1012859.1243220812,"type": 255736.22537361202],"properties": [1012206.7668110086},
{"geometry":"{u'type': u'MultiPolygon',"id": u'coordinates': [[[[1029378.6709997699,"type": 236734.16803964457],"properties": [1029450.5036397693},
{"geometry":"{u'type': u'Polygon',"id": u'coordinates': [[[1008935.6437906276,"type": 253212.86910867714],"properties": [1009181.3015595316},
{"geometry":"{u'type': u'Polygon',"id": u'coordinates': [[[982140.3101205898,"type": 163955.09304827073],"properties": [981979.8224265389},
{"geometry":"{u'type': u'Polygon',"id": u'coordinates': [[[987009.9975471883,"type": 180147.31187669607],"properties": [987171.4445299838},
{"geometry":"{u'type': u'MultiPolygon',"id": u'coordinates': [[[[987171.4445299838,"type": 180351.35443941044],"properties": [987009.9975471883},
{"geometry":"{u'type': u'Polygon',"id": u'coordinates': [[[984115.5693676653,"type": 153273.70118720634],"properties": [984796.8793361569},
{"geometry":"{u'type': u'Polygon',"id": u'coordinates': [[[990344.3521722123,"type": 188791.6136909228],"properties": [990258.1405157339},
{"geometry":"{u'type': u'MultiPolygon',"id": u'coordinates': [[[[1002727.4444696881,"type": 170588.75897916124],"properties": [1002984.7170907805},
{"geometry":"{u'type': u'MultiPolygon',"id": u'coordinates': [[[[996987.5611052224,"type": 151720.6380190194],"properties": [996925.9013930545},
{"geometry":"{u'type': u'Polygon',"id": u'coordinates': [[[980998.2361295044,"type": 162512.48735142464],"properties": [981172.0689796457},
{"geometry":"{u'type': u'Polygon',"id": u'coordinates': [[[1014393.6403369212,"type": 176969.23422111687],"properties": [1014090.3089899599},
{"geometry":"{u'type': u'Polygon',"id": u'coordinates': [[[994169.6897576773,"type": 165155.29389538008],"properties": [994275.2032885705},
{"geometry":"{u'type': u'Polygon',"id": u'coordinates': [[[998749.776683691,"type": 183272.3164143949],"properties": [997981.051404125},
{"geometry":"{u'type': u'Polygon',"id": u'coordinates': [[[995875.4439056884,"type": 174823.09976406908],"properties": [995895.0813595601},
{"geometry":"{u'type': u'Polygon',"id": u'coordinates': [[[995908.132545959,"type": 183617.62763608128],"properties": [996658.6061902924},
{"geometry":"{u'type': u'Polygon',"id": u'coordinates': [[[994912.5702637472,"type": 203747.47976902945],"properties": [994884.6447043587},
{"geometry":"{u'type': u'Polygon',"id": u'coordinates': [[[1005182.4536600389,"type": 181148.2354564453],"properties": [1004673.9713031156},
{"geometry":"{u'type': u'Polygon',"id": u'coordinates': [[[1007003.1753137348,"type": 186544.48553951882],"properties": [1006703.0413933576},
{"geometry":"{u'type': u'Polygon',"id": u'coordinates': [[[995875.4439056884,"type": 174823.09976406908],"properties": [995865.8371364455},
{"geometry":"{u'type': u'Polygon',"id": u'coordinates': [[[1001785.8085311688,"type": 193521.43775321558],"properties": [1001610.7462395802},
{"geometry":"{u'type': u'Polygon',"id": u'coordinates': [[[1010415.997319319,"type": 204756.7769903198],"properties": [1010796.5052063371},
{"geometry":"{u'type': u'Polygon',"id": u'coordinates': [[[1021235.0878441692,"type": 202161.87084734693],"properties": [1021084.5247097204},
{"geometry":"{u'type': u'Polygon',"id": u'coordinates': [[[1016887.166966452,"type": 208060.35801526904],"properties": [1016912.1159518837},
{"geometry":"{u'type': u'Polygon',"id": u'coordinates': [[[1016528.7691077206,"type": 206658.65869037822],"properties": [1016763.9480986204},
{"geometry":"{u'type': u'Polygon',"id": u'coordinates': [[[1015896.5307974835,"type": 211609.82738481998],"properties": [1015638.889988818},
{"geometry":"{u'type': u'Polygon',"id": u'coordinates': [[[1007008.721023959,"type": 225275.47895729172],"properties": [1007423.8232677086},
{"geometry":"{u'type': u'Polygon',"id": u'coordinates': [[[1024373.625956493,"type": 195010.30458139227],"properties": [1024372.8960868317},
{"geometry":"{u'type': u'Polygon',"id": u'coordinates': [[[1034013.7707569947,"type": 198040.06554627194],"properties": [1033841.835937256},
{"geometry":"{u'type': u'Polygon',"id": u'coordinates': [[[1047626.5604735338,"type": 182715.97406298408],"properties": [1047104.9625201832},
{"geometry":"{u'type': u'MultiPolygon',"id": u'coordinates': [[[[1024294.427315204,"type": 181150.3527789403],"properties": [1024181.5995236136},
{"geometry":"{u'type': u'Polygon',"id": u'coordinates': [[[1065864.3288482504,"type": 214337.23157409127],"properties": [1066362.798612072},
{"geometry":"{u'type': u'Polygon',"id": u'coordinates': [[[1053257.6718278634,"type": 224601.86032076727],"properties": [1053302.7178171515},
{"geometry":"{u'type': u'MultiPolygon',"id": u'coordinates': [[[[1030364.3795309013,"type": 209908.25258479634],"properties": [1029727.0330217016},
{"geometry":"{u'type': u'MultiPolygon',"id": u'coordinates': [[[[1029704.9572605387,"type": 169249.62118578897],"properties": [1029605.5688970333}
}
